stf_appium_client/AdbServer.py
stf_appium_client/AppiumClient.py
stf_appium_client/AppiumServer.py
stf_appium_client/Logger.py
stf_appium_client/StfClient.py
stf_appium_client/__init__.py
stf_appium_client/cli.py
stf_appium_client/exceptions.py
stf_appium_client/tools.py
stf_appium_client-0.13.0.dist-info/LICENSE
stf_appium_client-0.13.0.dist-info/METADATA
stf_appium_client-0.13.0.dist-info/WHEEL
stf_appium_client-0.13.0.dist-info/entry_points.txt
stf_appium_client-0.13.0.dist-info/top_level.txt
stf_appium_client-0.13.0.dist-info/RECORD
