Metadata-Version: 2.1
Name: stf-appium-client
Version: 0.13.0
Summary: STF client with appium
Home-page: https://github.com/OpenTMI/stf-appium-python-client
Author: Jussi Vatjus-Anttila
Author-email: jussiva@gmail.com
License: MIT
Project-URL: Homepage, https://github.com/OpenTMI/stf-appium-python-client
Project-URL: Bug Reports, https://github.com/OpenTMI/stf-appium-python-client/issues
Project-URL: Source, https://github.com/OpenTMI/stf-appium-python-client
Keywords: DeviceFarmer STF appium pytest robot-framework lockable resource android
Classifier: Development Status :: 3 - Alpha
Classifier: Topic :: Software Development :: Testing
Classifier: Operating System :: OS Independent
Classifier: License :: OSI Approved :: Apache Software License
Classifier: Operating System :: POSIX
Classifier: Operating System :: Microsoft :: Windows
Classifier: Operating System :: MacOS :: MacOS X
Classifier: Programming Language :: Python
Classifier: Programming Language :: Python :: 3
Classifier: Programming Language :: Python :: 3.9
Classifier: Programming Language :: Python :: 3.10
Classifier: Programming Language :: Python :: 3.11
Classifier: Programming Language :: Python :: 3.12
Classifier: Topic :: Software Development :: Testing
Requires-Python: >=3.9
License-File: LICENSE
Requires-Dist: Appium-Python-Client
Requires-Dist: stf-client==0.1.0
Requires-Dist: pydash
Requires-Dist: easyprocess
Requires-Dist: requests
Provides-Extra: dev
Requires-Dist: wheel; extra == "dev"
Requires-Dist: mock; extra == "dev"
Requires-Dist: pylint; extra == "dev"
Requires-Dist: pytest; extra == "dev"
Requires-Dist: pytest-cov; extra == "dev"
Requires-Dist: pytest-mock; extra == "dev"
Requires-Dist: pyinstaller; extra == "dev"
Requires-Dist: coveralls; extra == "dev"
